tsigna/__init__.py
tsigna/config.toml
tsigna/main.py
tsigna-0.2.0.dist-info/METADATA
tsigna-0.2.0.dist-info/WHEEL
tsigna-0.2.0.dist-info/entry_points.txt
tsigna-0.2.0.dist-info/licenses/LICENSE
tsigna-0.2.0.dist-info/RECORD
