Metadata-Version: 2.4
Name: tsigna
Version: 0.2.0
Summary: Terminal tool to plot stocks, crypto, pair ratios, and technical indicators like MACD and RSI.
Project-URL: Repository, https://github.com/monsieurlinux/tsigna
Author-email: Monsieur Linux <info@mlinux.ca>
License-Expression: MIT
License-File: LICENSE
Keywords: bitcoin,cli,cryptocurrency,finance,python,stock-market,terminal,trading
Classifier: Operating System :: OS Independent
Classifier: Programming Language :: Python :: 3
Requires-Python: >=3.11
Requires-Dist: pandas<3.0.0,>=2.0.0
Requires-Dist: plotille>=5.0.0
Requires-Dist: yahooquery>=2.4.1
